afesta_tools/__init__.py
afesta_tools/__main__.py
afesta_tools/config.py
afesta_tools/exceptions.py
afesta_tools/lpeg/__init__.py
afesta_tools/lpeg/client.py
afesta_tools/lpeg/credentials.py
afesta_tools/progress.py
afesta_tools/py.typed
afesta_tools/types.py
afesta_tools/utils.py
afesta_tools/vcs/__init__.py
afesta_tools/vcs/archive.py
afesta_tools/vcs/goods.py
afesta_tools-0.1.3.dist-info/LICENSE.rst
afesta_tools-0.1.3.dist-info/METADATA
afesta_tools-0.1.3.dist-info/WHEEL
afesta_tools-0.1.3.dist-info/entry_points.txt
afesta_tools-0.1.3.dist-info/RECORD
