Metadata-Version: 2.1
Name: afesta-tools
Version: 0.1.3
Summary: Afesta Tools
Home-page: https://github.com/bhrevol/afesta-tools
License: MIT
Author: byeonhyeok
Author-email: bhrevol@gmail.com
Requires-Python: >=3.8,<4.0
Classifier: Development Status :: 3 - Alpha
Classifier: License :: OSI Approved :: MIT License
Classifier: Programming Language :: Python :: 3
Classifier: Programming Language :: Python :: 3.8
Classifier: Programming Language :: Python :: 3.9
Classifier: Programming Language :: Python :: 3.10
Classifier: Programming Language :: Python :: 3.11
Requires-Dist: a10sa-script (>=0.1.2,<0.2.0)
Requires-Dist: aiohttp (>=3.8.1,<4.0.0)
Requires-Dist: click (>=8.0.1)
Requires-Dist: fake-winreg (>=1.6.0,<2.0.0)
Requires-Dist: funcy (>=1.17,<2.0)
Requires-Dist: loguru (>=0.7.2,<0.8.0)
Requires-Dist: lxml (>=4.7.1,<5.0.0)
Requires-Dist: platformdirs (>=3.0.0,<4.0.0)
Requires-Dist: tqdm (>=4.62.3,<5.0.0)
Requires-Dist: typing-extensions (>=4.0.1,<5.0.0)
Project-URL: Changelog, https://github.com/bhrevol/afesta-tools/releases
Project-URL: Documentation, https://afesta-tools.readthedocs.io
Project-URL: Repository, https://github.com/bhrevol/afesta-tools
